minebot/__init__.py
minebot/github_manager.py
minebot/stock_data.py
minebot-0.1.4.4.dist-info/METADATA
minebot-0.1.4.4.dist-info/WHEEL
minebot-0.1.4.4.dist-info/top_level.txt
minebot-0.1.4.4.dist-info/RECORD
