Metadata-Version: 2.4
Name: minebot
Version: 0.1.4.4
Summary: MineBot Google Drive utilities
Home-page: https://github.com/KoreanSniper/minebot
Author: KoreanSniper
Author-email: ytkoreansniper@gmail.com
Classifier: Programming Language :: Python :: 3
Classifier: License :: OSI Approved :: MIT License
Requires-Python: >=3.7
Requires-Dist: requests>=2.0.0
Dynamic: author
Dynamic: author-email
Dynamic: classifier
Dynamic: description
Dynamic: description-content-type
Dynamic: home-page
Dynamic: requires-dist
Dynamic: requires-python
Dynamic: summary
